{"trial_id": "87d33ba7cdd41f4e308003d1f0cc4e16", "hyperparameters": {"space": [{"class_name": "Int", "config": {"name": "kernel_size_t", "default": null, "conditions": [], "min_value": 2, "max_value": 8, "step": 2, "sampling": null}}, {"class_name": "Int", "config": {"name": "kernel_size_f", "default": null, "conditions": [], "min_value": 2, "max_value": 16, "step": 2, "sampling": null}}, {"class_name": "Int", "config": {"name": "filters_1", "default": null, "conditions": [], "min_value": 16, "max_value": 64, "step": 8, "sampling": null}}, {"class_name": "Int", "config": {"name": "filters_2", "default": null, "conditions": [], "min_value": 16, "max_value": 64, "step": 8, "sampling": null}}, {"class_name": "Int", "config": {"name": "filters_3", "default": null, "conditions": [], "min_value": 16, "max_value": 64, "step": 8, "sampling": null}}, {"class_name": "Int", "config": {"name": "filters_4", "default": null, "conditions": [], "min_value": 16, "max_value": 64, "step": 8, "sampling": null}}, {"class_name": "Choice", "config": {"name": "pooling_size_t", "default": 1, "conditions": [], "values": [1, 2], "ordered": true}}, {"class_name": "Choice", "config": {"name": "pooling_size_f", "default": 1, "conditions": [], "values": [1, 2], "ordered": true}}, {"class_name": "Float", "config": {"name": "drop_out_1", "default": 0.1, "conditions": [], "min_value": 0.1, "max_value": 0.5, "step": 0.1, "sampling": null}}, {"class_name": "Float", "config": {"name": "drop_out_2", "default": 0.1, "conditions": [], "min_value": 0.1, "max_value": 0.5, "step": 0.1, "sampling": null}}], "values": {"kernel_size_t": 6, "kernel_size_f": 10, "filters_1": 56, "filters_2": 40, "filters_3": 56, "filters_4": 24, "pooling_size_t": 1, "pooling_size_f": 2, "drop_out_1": 0.1, "drop_out_2": 0.4, "tuner/epochs": 20, "tuner/initial_epoch": 7, "tuner/bracket": 1, "tuner/round": 1, "tuner/trial_id": "3b29bfb0e32e25bfd60e76673e8154a6"}}, "metrics": {"metrics": {"loss": {"direction": "min", "observations": [{"value": [1.4129571914672852], "step": 0}]}, "true_negatives_1": {"direction": "min", "observations": [{"value": [58217.0], "step": 0}]}, "true_positives_1": {"direction": "min", "observations": [{"value": [8331.0], "step": 0}]}, "false_negatives_1": {"direction": "min", "observations": [{"value": [7163.0], "step": 0}]}, "false_positives_1": {"direction": "min", "observations": [{"value": [1301.0], "step": 0}]}, "precision_1": {"direction": "min", "observations": [{"value": [0.9587984681129456], "step": 0}]}, "recall_1": {"direction": "min", "observations": [{"value": [0.9445578455924988], "step": 0}]}, "categorical_accuracy": {"direction": "max", "observations": [{"value": [0.9512471556663513], "step": 0}]}, "val_loss": {"direction": "min", "observations": [{"value": [0.941608726978302], "step": 0}]}, "val_true_negatives_1": {"direction": "min", "observations": [{"value": [5843.0], "step": 0}]}, "val_true_positives_1": {"direction": "min", "observations": [{"value": [931.0], "step": 0}]}, "val_false_negatives_1": {"direction": "min", "observations": [{"value": [567.0], "step": 0}]}, "val_false_positives_1": {"direction": "min", "observations": [{"value": [186.0], "step": 0}]}, "val_precision_1": {"direction": "min", "observations": [{"value": [0.961737334728241], "step": 0}]}, "val_recall_1": {"direction": "min", "observations": [{"value": [0.949999988079071], "step": 0}]}, "val_categorical_accuracy": {"direction": "max", "observations": [{"value": [0.9561224579811096], "step": 0}]}}}, "score": 0.9512471556663513, "best_step": 0, "status": "COMPLETED"}